[
    {
        "headline": "Israeli strike hits Rafah after Hamas rocket barrage",
        "location": "Israel"
    },
    {
        "headline": "UN fears 670 people buried under Papua landslide",
        "location": "Indonesia"
    },
    {
        "headline": "Colombia begins exploring \u2018holy grail of shipwrecks\u2019",
        "location": "Colombia"
    },
    {
        "headline": "Tornadoes and storms leave 15 dead across central US",
        "location": "USA"
    },
    {
        "headline": "The ANC hopes to conquer but will it struggle in South Africa poll?",
        "location": "South Africa"
    },
    {
        "headline": "UN fears 670 people buried under Papua landslide",
        "location": "Indonesia"
    },
    {
        "headline": "Some 160 villagers reported taken in deadly raid in Nigeria",
        "location": "Nigeria"
    },
    {
        "headline": "'We saw the flight attendant just go up in the air'",
        "location": "USA"
    },
    {
        "headline": "Colombia begins exploring \u2018holy grail of shipwrecks\u2019",
        "location": "Colombia"
    },
    {
        "headline": "130 people die at Sudan hospital amid city siege",
        "location": "Sudan"
    },
    {
        "headline": "Turbulence on Doha-Dublin flight leaves 12 injured",
        "location": "Qatar/Dublin"
    },
    {
        "headline": "Suspected Sinaloa cartel assassin extradited to US",
        "location": "Mexico/USA"
    },
    {
        "headline": "Newborn babies die after fire at Delhi hospital",
        "location": "India"
    },
    {
        "headline": "Burkina Faso extends military rule by five years",
        "location": "Burkina Faso"
    },
    {
        "headline": "Israel-Gaza war",
        "location": "Israel/Gaza"
    },
    {
        "headline": "Top UN court orders Israel to stop Rafah offensive",
        "location": "Palestine"
    },
    {
        "headline": "Three more Israeli hostages' bodies found in Gaza",
        "location": "Israel"
    },
    {
        "headline": "Ireland, Norway and Spain to recognise Palestinian state",
        "location": "Ireland/Norway/Spain"
    },
    {
        "headline": "UN halts Rafah food distribution due to shortages and hostilities",
        "location": "Palestine"
    },
    {
        "headline": "Israel revokes decision to shut down Associated Press news agency's Gaza live feed",
        "location": "Israel"
    },
    {
        "headline": "Watch/Listen",
        "location": "No country specified"
    },
    {
        "headline": "Watch: Airport employee informs Nicki Minaj of bag search",
        "location": "No country specified"
    },
    {
        "headline": "Boos and jeers for Trump at Libertarian convention",
        "location": "USA"
    },
    {
        "headline": "Watch: BBC's Jeremy Bowen at the site of Kharkiv strike",
        "location": "Ukraine"
    },
    {
        "headline": "\u2018If they see us they will bomb us\u2019 - watch as BBC reaches a hidden war\u2019s jungle front line",
        "location": "Ukraine"
    },
    {
        "headline": "Watch: Smoke and flames at deadly India arcade fire",
        "location": "India"
    },
    {
        "headline": "Features",
        "location": "No country specified"
    },
    {
        "headline": "Meet the Peaky Blinders - Ukraine's drone squad defending Kharkiv",
        "location": "Ukraine"
    },
    {
        "headline": "How plans for \u2018the day after\u2019 could help end war in Gaza",
        "location": "Gaza/Israel"
    },
    {
        "headline": "Far right eyes Europe vote surge and ditches German AfD",
        "location": "Germany/Europe"
    },
    {
        "headline": "Veteran sketch artists have never seen a trial like Trump's",
        "location": "USA"
    },
    {
        "headline": "How film stars faded - and pop stars took over",
        "location": "UK"
    },
    {
        "headline": "Latest updates",
        "location": "No country specified"
    },
    {
        "headline": "Priced out of homeownership - 'It makes me want to throw up'",
        "location": "UK"
    },
    {
        "headline": "Israeli strike hits Rafah after Hamas rocket barrage",
        "location": "Israel"
    },
    {
        "headline": "Passengers recall 'panic' as plane hit turbulence",
        "location": "Qatar/Dublin"
    },
    {
        "headline": "Turbulence on Doha-Dublin flight leaves 12 injured",
        "location": "Qatar/Dublin"
    },
    {
        "headline": "Hamas launches rocket attack towards Tel Aviv",
        "location": "Israel"
    },
    {
        "headline": "Tornadoes and storms leave 15 dead across central US",
        "location": "USA"
    },
    {
        "headline": "130 people die at Sudan hospital amid city siege",
        "location": "Sudan"
    },
    {
        "headline": "Newborn babies die after fire at Delhi hospital",
        "location": "India"
    },
    {
        "headline": "Trump booed at Libertarian convention",
        "location": "USA"
    },
    {
        "headline": "Papua New Guinea struggles to find the estimated 670 killed in landslide",
        "location": "Papua New Guinea"
    },
    {
        "headline": "China attempts to counter Japan and South Korea\u2019s closer ties with U.S.",
        "location": "China/Japan/South Korea"
    },
    {
        "headline": "Israel strikes hit Rafah camp after Hamas fires rockets toward Tel Aviv",
        "location": "Israel"
    },
    {
        "headline": "Far-right Israeli settlers step up attacks on aid trucks bound for Gaza",
        "location": "Israel"
    },
    {
        "headline": "These Ukrainians were musicians before the war. Now they fight with song.",
        "location": "Ukraine"
    },
    {
        "headline": "U.S. silent as global condemnation of Israel\u2019s Rafah offensive grows",
        "location": "USA"
    },
    {
        "headline": "Russia bombs market in Kharkiv, killing at least 6 and wounding 40",
        "location": "Ukraine"
    },
    {
        "headline": "U.N. chief \u2018trusts\u2019 Israel will comply with ICJ order to halt Rafah assault",
        "location": "UN/Palestine"
    },
    {
        "headline": "Loggers encroach on an uncontacted tribe, and the government shrugs",
        "location": "Brazil"
    },
    {
        "headline": "The United States used to have cachet in China. Not anymore.",
        "location": "China"
    },
    {
        "headline": "Orcas aren\u2019t attacking boats \u2014 they\u2019re just playful teens, scientists say",
        "location": "USA"
    },
    {
        "headline": "Three missionaries from Oklahoma-based group shot to death in Haiti",
        "location": "USA/Haiti"
    },
    {
        "headline": "ICJ orders Israel \u2018to immediately halt\u2019 Rafah offensive",
        "location": "UN/Palestine"
    },
    {
        "headline": "U.N. court order deepens Israel\u2019s isolation as it fights on in Rafah",
        "location": "Palestine"
    },
    {
        "headline": "What is the ICJ, the U.N. court ordering Israel to halt Rafah offensive?",
        "location": "UN"
    },
    {
        "headline": "Can a precocious prime minister hold off a far-right phenom in France?",
        "location": "France"
    },
    {
        "headline": "Russian jamming leaves some high-tech U.S. weapons ineffective in Ukraine",
        "location": "Russia/Ukraine"
    },
    {
        "headline": "How many hostages are still in Gaza since Hamas attack on Israel? What to know.",
        "location": "Israel"
    },
    {
        "headline": "Israel\u2019s isolation deepens on the world stage",
        "location": "Israel"
    },
    {
        "headline": "Pope clears way for first millennial saint, dubbed \u2018God\u2019s Influencer\u2019",
        "location": "Vatican City"
    }
]