[
    {
        "headline": "Buenos Aires rocked by clashes over Milei reforms",
        "location": "Argentina",
        "coordinates": [
            -34.9964963,
            -64.9672817
        ]
    },
    {
        "headline": "Stranded surfer rescued after spelling out 'HELP'",
        "location": "Australia",
        "coordinates": [
            -24.7761086,
            134.755
        ]
    },
    {
        "headline": "Holly Valance: From Aussie pop star to Trump cheerleader",
        "location": "Australia",
        "coordinates": [
            -24.7761086,
            134.755
        ]
    },
    {
        "headline": "\u2018I am not quite myself,\u2019 Danish prime minister says following attack",
        "location": "Denmark",
        "coordinates": [
            55.670249,
            10.3333283
        ]
    },
    {
        "headline": "French right ditch leader over far-right alliance deal",
        "location": "France",
        "coordinates": [
            46.603354,
            1.8883335
        ]
    },
    {
        "headline": "Snap elections are an 'act of trust', says Macron",
        "location": "France",
        "coordinates": [
            46.603354,
            1.8883335
        ]
    },
    {
        "headline": "Macron defends decision to call elections, slams possible alliance on the right",
        "location": "France",
        "coordinates": [
            46.603354,
            1.8883335
        ]
    },
    {
        "headline": "A 28-year-old is the face of France\u2019s far right: Who is Jordan Bardella?",
        "location": "France",
        "coordinates": [
            46.603354,
            1.8883335
        ]
    },
    {
        "headline": "As Europe faces war, Germany looks to restore national service",
        "location": "Germany",
        "coordinates": [
            51.1638175,
            10.4478313
        ]
    },
    {
        "headline": "Israel shrugs at Palestinian civilian casualties. So does Hamas.",
        "location": "Israel",
        "coordinates": [
            30.8124247,
            34.8594762
        ]
    },
    {
        "headline": "Seven new ice cream flavours and the Pope: Italy prepares to host G7",
        "location": "Italy",
        "coordinates": [
            42.6384261,
            12.674297
        ]
    },
    {
        "headline": "Seven new ice cream flavours and the Pope: Italy prepares to host G7",
        "location": "Italy",
        "coordinates": [
            42.6384261,
            12.674297
        ]
    },
    {
        "headline": "Hezbollah fires dozens of rockets into Israel after strike kills commander",
        "location": "Lebanon",
        "coordinates": [
            40.375713,
            -76.4626118
        ]
    },
    {
        "headline": "Hezbollah lobs rockets at Israel as U.S. accuses Hamas of prolonging Gaza war",
        "location": "Lebanon",
        "coordinates": [
            40.375713,
            -76.4626118
        ]
    },
    {
        "headline": "Why another coup is so unlikely in Nigeria",
        "location": "Nigeria",
        "coordinates": [
            9.6000359,
            7.9999721
        ]
    },
    {
        "headline": "First BTS member finishes military service, pledges hugs for 1,000 fans",
        "location": "South Korea",
        "coordinates": [
            36.638392,
            127.6961188
        ]
    },
    {
        "headline": "Rodeo bull escapes and hurls bystander into the air",
        "location": "Spain",
        "coordinates": [
            39.3260685,
            -4.8379791
        ]
    },
    {
        "headline": "The hit Thai film moving TikTokers to tears",
        "location": "Thailand",
        "coordinates": [
            7.4931858,
            124.724704
        ]
    },
    {
        "headline": "Gaza ceasefire plan in balance as US says Hamas proposed 'changes'",
        "location": "USA",
        "coordinates": [
            39.7837304,
            -100.445882
        ]
    },
    {
        "headline": "US widens Russia sanctions in banking crackdown",
        "location": "USA",
        "coordinates": [
            39.7837304,
            -100.445882
        ]
    },
    {
        "headline": "Oklahoma court rejects Tulsa Massacre survivors suit",
        "location": "USA",
        "coordinates": [
            39.7837304,
            -100.445882
        ]
    },
    {
        "headline": "Transgender swimmer Thomas' legal case over ban dismissed",
        "location": "USA",
        "coordinates": [
            39.7837304,
            -100.445882
        ]
    },
    {
        "headline": "Drugs, alcohol and a gun: Inside Hunter Biden's trial",
        "location": "USA",
        "coordinates": [
            39.7837304,
            -100.445882
        ]
    },
    {
        "headline": "'Hunter Biden\u2019s story is a story that all too many Americans know'",
        "location": "USA",
        "coordinates": [
            39.7837304,
            -100.445882
        ]
    },
    {
        "headline": "'I've been stabbed': US teacher recounts China attack",
        "location": "USA",
        "coordinates": [
            39.7837304,
            -100.445882
        ]
    },
    {
        "headline": "White House does not rule out Hunter Biden commutation",
        "location": "USA",
        "coordinates": [
            39.7837304,
            -100.445882
        ]
    },
    {
        "headline": "Sandy Hook survivors to graduate high school",
        "location": "USA",
        "coordinates": [
            39.7837304,
            -100.445882
        ]
    },
    {
        "headline": "Sandy Hook survivors graduate: 'Chunk of our class missing'",
        "location": "USA",
        "coordinates": [
            39.7837304,
            -100.445882
        ]
    },
    {
        "headline": "Merrick Garland held in contempt of US Congress",
        "location": "USA",
        "coordinates": [
            39.7837304,
            -100.445882
        ]
    },
    {
        "headline": "Oklahoma court rejects Tulsa Massacre survivors suit",
        "location": "USA",
        "coordinates": [
            39.7837304,
            -100.445882
        ]
    },
    {
        "headline": "Georgia gunman hijacks commuter bus, leaves one dead",
        "location": "USA",
        "coordinates": [
            39.7837304,
            -100.445882
        ]
    },
    {
        "headline": "Biden\u2019s new measures to stem illegal border crossings draw legal challenge",
        "location": "USA",
        "coordinates": [
            39.7837304,
            -100.445882
        ]
    },
    {
        "headline": "U.S. will send Ukraine a second Patriot air defense battery",
        "location": "USA",
        "coordinates": [
            39.7837304,
            -100.445882
        ]
    },
    {
        "headline": "What is Biden\u2019s proposed cease-fire deal? Here\u2019s the plan to end war in Gaza.",
        "location": "USA",
        "coordinates": [
            39.7837304,
            -100.445882
        ]
    },
    {
        "headline": "U.S. lifts weapons ban on Ukrainian military unit",
        "location": "USA",
        "coordinates": [
            39.7837304,
            -100.445882
        ]
    },
    {
        "headline": "Global poll finds Biden more popular than Trump",
        "location": "USA",
        "coordinates": [
            39.7837304,
            -100.445882
        ]
    },
    {
        "headline": "Russian missile strike kills 9 in Zelensky's hometown - officials",
        "location": "Ukraine",
        "coordinates": [
            49.4871968,
            31.2718321
        ]
    },
    {
        "headline": "\u2018Ram him\u2019: How Ukraine is pushing U.S. combat gear to the extreme",
        "location": "Ukraine",
        "coordinates": [
            49.4871968,
            31.2718321
        ]
    },
    {
        "headline": "Houthis claim attack on merchant ship in Red Sea",
        "location": "Yemen",
        "coordinates": [
            16.3471243,
            47.8915271
        ]
    },
    {
        "headline": "Houthis claim attack on merchant ship in Red Sea",
        "location": "Yemen",
        "coordinates": [
            16.3471243,
            47.8915271
        ]
    }
]